passboltapi/__init__.py
passboltapi/schema.py
passbolt_python_api-0.3.8.dist-info/LICENSE
passbolt_python_api-0.3.8.dist-info/METADATA
passbolt_python_api-0.3.8.dist-info/WHEEL
passbolt_python_api-0.3.8.dist-info/top_level.txt
passbolt_python_api-0.3.8.dist-info/RECORD
