Metadata-Version: 2.1
Name: passbolt-python-api
Version: 0.3.8
Summary: A python client for Passbolt.
Home-page: https://github.com/shubhamdipt/passbolt-python-api
Author: Shubham Dipt
Author-email: shubham.dipt@gmail.com
License: MIT
Platform: any
Classifier: Programming Language :: Python :: 3
Classifier: License :: OSI Approved :: MIT License
Classifier: Operating System :: OS Independent
License-File: LICENSE
Requires-Dist: certifi (>=2019.6.16)
Requires-Dist: chardet (>=3.0.4)
Requires-Dist: charset-normalizer (>=2.0.8)
Requires-Dist: idna (>=2.8)
Requires-Dist: python-gnupg (>=0.4.7)
Requires-Dist: requests (>=2.26.0)
Requires-Dist: typing-extensions (>=4.0.0)
Requires-Dist: urllib3 (>=1.25.3)
